MANIFEST.in
README.rst
buildout.cfg
requirements.txt
setup.py
version.txt
bob/__init__.py
bob.paper.isba2018_pad_dnn.egg-info/PKG-INFO
bob.paper.isba2018_pad_dnn.egg-info/SOURCES.txt
bob.paper.isba2018_pad_dnn.egg-info/dependency_links.txt
bob.paper.isba2018_pad_dnn.egg-info/entry_points.txt
bob.paper.isba2018_pad_dnn.egg-info/not-zip-safe
bob.paper.isba2018_pad_dnn.egg-info/requires.txt
bob.paper.isba2018_pad_dnn.egg-info/top_level.txt
bob/paper/__init__.py
bob/paper/isba2018_pad_dnn/__init__.py
bob/paper/isba2018_pad_dnn/plot_far_frr_pad.py
bob/paper/isba2018_pad_dnn/plot_pad_results.py
doc/conf.py
doc/index.rst
doc/img/favicon.ico
doc/img/logo.png