Metadata-Version: 1.1
Name: bob.paper.isba2018-pad-dnn
Version: 1.0.2
Summary: "On the Use of Convolutional Neural Networks for Speech Presentation Attack Detection" published in ISBA 2018
Home-page: http://gitlab.idiap.ch/bob/bob.paper.isba2018-pad-dnn
Author: Pavel Korshunov
Author-email: pavel.korshunov@idiap.ch
License: BSD
Platform: UNKNOWN
Classifier: Framework :: Bob
Classifier: Development Status :: 4 - Beta
Classifier: Intended Audience :: Science/Research
Classifier: License :: OSI Approved :: BSD License
Classifier: Natural Language :: English
Classifier: Programming Language :: Python
Classifier: Programming Language :: Python :: 3
Classifier: Topic :: Scientific/Engineering :: Artificial Intelligence
Classifier: Topic :: Database :: Front-Ends
